bot_brawl-0.1.1.dist-info/METADATA
bot_brawl-0.1.1.dist-info/WHEEL
bot_brawl/__init__.py
bot_brawl/__init__.pyi
bot_brawl/bot_brawl.cp312-win_amd64.pyd
bot_brawl/py.typed
bot_brawl-0.1.1.dist-info/RECORD
