Metadata-Version: 2.4
Name: bot_brawl
Version: 0.1.1
Summary: Python bindings for arena-core Rust library
Requires-Python: >=3.11
